Metadata-Version: 1.0
Name: pysafelogging
Version: 0.1
Summary: Safe logging for python
Home-page: https://github.com/vovict/pysafelogging
Author: UNKNOWN
Author-email: UNKNOWN
License: UNKNOWN
Platform: UNKNOWN
